Metadata-Version: 2.1
Name: llm-as-function
Version: 0.0.1b3
Summary: Embed your LLM into a python function
Home-page: https://github.com/gusye1234/llm-as-function
Author: JianbaiYe
Classifier: Programming Language :: Python :: 3
Classifier: License :: OSI Approved :: MIT License
Classifier: Operating System :: OS Independent
Requires-Python: >=3.9
